examples/__init__.py
examples/models.py
tortoise_cli-0.2.0.dist-info/METADATA
tortoise_cli-0.2.0.dist-info/WHEEL
tortoise_cli-0.2.0.dist-info/entry_points.txt
tortoise_cli-0.2.0.dist-info/licenses/LICENSE
tortoise_cli/__init__.py
tortoise_cli/cli.py
tortoise_cli/utils.py
tortoise_cli-0.2.0.dist-info/RECORD
