Metadata-Version: 2.4
Name: tortoise-cli
Version: 0.2.0
Summary: A cli tool for tortoise-orm, build on top of click and ptpython.
Keywords: tortoise,shell,cli,tortoise-orm
Author-Email: long2ice <long2ice@gmail.com>
License-Expression: Apache-2.0
Project-URL: homepage, https://github.com/tortoise/tortoise-cli
Project-URL: repository, https://github.com/tortoise/tortoise-cli.git
Project-URL: documentation, https://github.com/tortoise/tortoise-cli
Requires-Python: >=3.9
Requires-Dist: tortoise-orm
Requires-Dist: ptpython
Requires-Dist: asyncclick<9.0.0,>=8.1.7
Requires-Dist: tomlkit<1.0.0,>=0.11.4; python_version < "3.11"
